fastapi_proxy_lib/__init__.py
fastapi_proxy_lib/py.typed
fastapi_proxy_lib/core/__init__.py
fastapi_proxy_lib/core/_model.py
fastapi_proxy_lib/core/_tool.py
fastapi_proxy_lib/core/http.py
fastapi_proxy_lib/core/tool.py
fastapi_proxy_lib/core/websocket.py
fastapi_proxy_lib/fastapi/__init__.py
fastapi_proxy_lib/fastapi/app.py
fastapi_proxy_lib/fastapi/router.py
fastapi_proxy_lib-0.3.0.dist-info/METADATA
fastapi_proxy_lib-0.3.0.dist-info/WHEEL
fastapi_proxy_lib-0.3.0.dist-info/licenses/LICENSE
fastapi_proxy_lib-0.3.0.dist-info/RECORD
