Metadata-Version: 2.4
Name: fastapi-proxy-lib
Version: 0.3.0
Summary: HTTP/WebSocket proxy for starlette/FastAPI.
Project-URL: Documentation, https://WSH032.github.io/fastapi-proxy-lib/
Project-URL: Source code, https://github.com/WSH032/fastapi-proxy-lib
Author-email: Sean Wang <126865849+WSH032@users.noreply.github.com>
License: Apache License
License-File: LICENSE
Keywords: asgi,fastapi,forward-proxy,http,httpx,httpx-ws,proxy,reverse-proxy,starlette,websocket
Classifier: Environment :: Web Environment
Classifier: Framework :: AsyncIO
Classifier: Framework :: FastAPI
Classifier: Intended Audience :: Developers
Classifier: License :: OSI Approved :: Apache Software License
Classifier: Operating System :: OS Independent
Classifier: Programming Language :: Python :: 3 :: Only
Classifier: Programming Language :: Python :: 3.9
Classifier: Programming Language :: Python :: 3.10
Classifier: Programming Language :: Python :: 3.11
Classifier: Programming Language :: Python :: 3.12
Classifier: Programming Language :: Python :: 3.13
Classifier: Topic :: Internet :: WWW/HTTP :: HTTP Servers
Classifier: Topic :: Internet :: WWW/HTTP :: Session
Classifier: Typing :: Typed
Requires-Python: >=3.9
Requires-Dist: httpx
Requires-Dist: httpx-ws>=0.7.1
Requires-Dist: starlette
Requires-Dist: typing-extensions>=4.5.0
Provides-Extra: all
Requires-Dist: fastapi; extra == 'all'
Provides-Extra: standard
Requires-Dist: fastapi; extra == 'standard'
